{
  "meta": {
    "dataset_path": "data/analysis/graded_occurrences_latest.jsonl",
    "excluded_error_rows": 5263,
    "excluded_ineligible_rows": 2674,
    "generated_at_utc": "2026-03-09T21:21:54.689617+00:00",
    "graded_rows": 32793,
    "graded_unique_signals": 32793,
    "total_rows": 40793
  },
  "rows": [
    {
      "avg_odds": -51.44174962931582,
      "bets_with_units": 11326,
      "losses": 7437,
      "n": 14470,
      "net_units": -2394.893000000006,
      "odds_count": 9442,
      "odds_sum": -485713.0,
      "pushes": 49,
      "roi": -0.21145090941197298,
      "sources_combo": "betql",
      "total_stake": 11326.0,
      "units_missing_count": 3144,
      "wilson_lower": 0.4761,
      "win_pct": 0.48429373829831496,
      "wins": 6984
    },
    {
      "avg_odds": -42.53964194373402,
      "bets_with_units": 5005,
      "losses": 3249,
      "n": 6294,
      "net_units": -1637.396000000002,
      "odds_count": 391,
      "odds_sum": -16633.0,
      "pushes": 11,
      "roi": -0.32715204795204833,
      "sources_combo": "action",
      "total_stake": 5005.0,
      "units_missing_count": 1289,
      "wilson_lower": 0.4705,
      "win_pct": 0.48289033901002704,
      "wins": 3034
    },
    {
      "avg_odds": -37.0,
      "bets_with_units": 2406,
      "losses": 1229,
      "n": 2423,
      "net_units": 22.295999999999957,
      "odds_count": 3,
      "odds_sum": -111.0,
      "pushes": 35,
      "roi": 0.009266832917705718,
      "sources_combo": "juicereel_sxebets",
      "total_stake": 2406.0,
      "units_missing_count": 17,
      "wilson_lower": 0.4653,
      "win_pct": 0.4853433835845896,
      "wins": 1159
    },
    {
      "avg_odds": -101.35164835164835,
      "bets_with_units": 1512,
      "losses": 972,
      "n": 1897,
      "net_units": -492.38800000000225,
      "odds_count": 364,
      "odds_sum": -36892.0,
      "pushes": 16,
      "roi": -0.32565343915344064,
      "sources_combo": "action|betql|oddstrader",
      "total_stake": 1512.0,
      "units_missing_count": 385,
      "wilson_lower": 0.4607,
      "win_pct": 0.48325358851674644,
      "wins": 909
    },
    {
      "avg_odds": -81.9013698630137,
      "bets_with_units": 1166,
      "losses": 759,
      "n": 1570,
      "net_units": -396.10100000000057,
      "odds_count": 730,
      "odds_sum": -59788.0,
      "pushes": 15,
      "roi": -0.339709262435678,
      "sources_combo": "action|betql",
      "total_stake": 1166.0,
      "units_missing_count": 404,
      "wilson_lower": 0.4871,
      "win_pct": 0.5118971061093247,
      "wins": 796
    },
    {
      "avg_odds": -106.24793388429752,
      "bets_with_units": 1177,
      "losses": 660,
      "n": 1411,
      "net_units": -191.06100000000154,
      "odds_count": 242,
      "odds_sum": -25712.0,
      "pushes": 7,
      "roi": -0.16232880203908373,
      "sources_combo": "action|betql|dimers|oddstrader",
      "total_stake": 1177.0,
      "units_missing_count": 234,
      "wilson_lower": 0.5038,
      "win_pct": 0.5299145299145299,
      "wins": 744
    },
    {
      "avg_odds": -121.25,
      "bets_with_units": 826,
      "losses": 367,
      "n": 829,
      "net_units": 25.24700000000003,
      "odds_count": 4,
      "odds_sum": -485.0,
      "pushes": 0,
      "roi": 0.030565375302663473,
      "sources_combo": "juicereel_nukethebooks",
      "total_stake": 826.0,
      "units_missing_count": 3,
      "wilson_lower": 0.5233,
      "win_pct": 0.5572979493365501,
      "wins": 462
    },
    {
      "avg_odds": -112.9551282051282,
      "bets_with_units": 493,
      "losses": 368,
      "n": 773,
      "net_units": -260.2070000000001,
      "odds_count": 156,
      "odds_sum": -17621.0,
      "pushes": 1,
      "roi": -0.5278032454361057,
      "sources_combo": "oddstrader",
      "total_stake": 493.0,
      "units_missing_count": 280,
      "wilson_lower": 0.4881,
      "win_pct": 0.5233160621761658,
      "wins": 404
    },
    {
      "avg_odds": -49.605095541401276,
      "bets_with_units": 376,
      "losses": 188,
      "n": 421,
      "net_units": -10.03400000000002,
      "odds_count": 157,
      "odds_sum": -7788.0,
      "pushes": 1,
      "roi": -0.026686170212766012,
      "sources_combo": "action|oddstrader",
      "total_stake": 376.0,
      "units_missing_count": 45,
      "wilson_lower": 0.5046,
      "win_pct": 0.5523809523809524,
      "wins": 232
    },
    {
      "avg_odds": -114.86666666666666,
      "bets_with_units": 226,
      "losses": 160,
      "n": 337,
      "net_units": -104.82799999999988,
      "odds_count": 15,
      "odds_sum": -1723.0,
      "pushes": 5,
      "roi": -0.4638407079646012,
      "sources_combo": "betql|oddstrader",
      "total_stake": 226.0,
      "units_missing_count": 111,
      "wilson_lower": 0.4644,
      "win_pct": 0.5180722891566265,
      "wins": 172
    },
    {
      "avg_odds": 6.75,
      "bets_with_units": 195,
      "losses": 123,
      "n": 229,
      "net_units": -49.18200000000003,
      "odds_count": 4,
      "odds_sum": 27.0,
      "pushes": 0,
      "roi": -0.2522153846153848,
      "sources_combo": "dimers|oddstrader",
      "total_stake": 195.0,
      "units_missing_count": 34,
      "wilson_lower": 0.3994,
      "win_pct": 0.462882096069869,
      "wins": 106
    },
    {
      "avg_odds": 119.76146788990826,
      "bets_with_units": 227,
      "losses": 116,
      "n": 227,
      "net_units": 19.652,
      "odds_count": 109,
      "odds_sum": 13054.0,
      "pushes": 0,
      "roi": 0.08657268722466961,
      "sources_combo": "dimers",
      "total_stake": 227.0,
      "units_missing_count": 0,
      "wilson_lower": 0.4247,
      "win_pct": 0.4889867841409692,
      "wins": 111
    },
    {
      "avg_odds": -101.89473684210526,
      "bets_with_units": 183,
      "losses": 112,
      "n": 198,
      "net_units": -45.10400000000006,
      "odds_count": 57,
      "odds_sum": -5808.0,
      "pushes": 0,
      "roi": -0.2464699453551916,
      "sources_combo": "action|dimers|oddstrader",
      "total_stake": 183.0,
      "units_missing_count": 15,
      "wilson_lower": 0.3672,
      "win_pct": 0.43434343434343436,
      "wins": 86
    },
    {
      "avg_odds": -102.7,
      "bets_with_units": 164,
      "losses": 73,
      "n": 164,
      "net_units": 3.8099999999999987,
      "odds_count": 10,
      "odds_sum": -1027.0,
      "pushes": 0,
      "roi": 0.023231707317073164,
      "sources_combo": "sportsline",
      "total_stake": 164.0,
      "units_missing_count": 0,
      "wilson_lower": 0.4784,
      "win_pct": 0.5548780487804879,
      "wins": 91
    },
    {
      "avg_odds": -62.30909090909091,
      "bets_with_units": 155,
      "losses": 84,
      "n": 161,
      "net_units": -17.780000000000005,
      "odds_count": 55,
      "odds_sum": -3427.0,
      "pushes": 0,
      "roi": -0.11470967741935487,
      "sources_combo": "action|dimers",
      "total_stake": 155.0,
      "units_missing_count": 6,
      "wilson_lower": 0.4025,
      "win_pct": 0.4782608695652174,
      "wins": 77
    },
    {
      "avg_odds": -49.81967213114754,
      "bets_with_units": 137,
      "losses": 80,
      "n": 140,
      "net_units": -26.95199999999999,
      "odds_count": 61,
      "odds_sum": -3039.0,
      "pushes": 0,
      "roi": -0.19672992700729922,
      "sources_combo": "covers",
      "total_stake": 137.0,
      "units_missing_count": 3,
      "wilson_lower": 0.3496,
      "win_pct": 0.42857142857142855,
      "wins": 60
    },
    {
      "avg_odds": -109.75,
      "bets_with_units": 90,
      "losses": 42,
      "n": 103,
      "net_units": 2.2769999999999975,
      "odds_count": 28,
      "odds_sum": -3073.0,
      "pushes": 0,
      "roi": 0.025299999999999972,
      "sources_combo": "action|betql|covers|dimers|oddstrader",
      "total_stake": 90.0,
      "units_missing_count": 13,
      "wilson_lower": 0.4957,
      "win_pct": 0.5922330097087378,
      "wins": 61
    },
    {
      "avg_odds": -109.03225806451613,
      "bets_with_units": 82,
      "losses": 42,
      "n": 93,
      "net_units": -5.058999999999998,
      "odds_count": 31,
      "odds_sum": -3380.0,
      "pushes": 1,
      "roi": -0.06169512195121949,
      "sources_combo": "action|betql|dimers",
      "total_stake": 82.0,
      "units_missing_count": 11,
      "wilson_lower": 0.442,
      "win_pct": 0.5434782608695652,
      "wins": 50
    },
    {
      "avg_odds": -103.5,
      "bets_with_units": 77,
      "losses": 36,
      "n": 87,
      "net_units": 1.3669999999999995,
      "odds_count": 2,
      "odds_sum": -207.0,
      "pushes": 1,
      "roi": 0.017753246753246747,
      "sources_combo": "betql|dimers|oddstrader",
      "total_stake": 77.0,
      "units_missing_count": 10,
      "wilson_lower": 0.4758,
      "win_pct": 0.5813953488372093,
      "wins": 50
    },
    {
      "avg_odds": -47.604166666666664,
      "bets_with_units": 55,
      "losses": 35,
      "n": 87,
      "net_units": -0.643000000000001,
      "odds_count": 48,
      "odds_sum": -2285.0,
      "pushes": 0,
      "roi": -0.01169090909090911,
      "sources_combo": "betql|juicereel_sxebets",
      "total_stake": 55.0,
      "units_missing_count": 32,
      "wilson_lower": 0.4926,
      "win_pct": 0.5977011494252874,
      "wins": 52
    },
    {
      "avg_odds": 64.3,
      "bets_with_units": 52,
      "losses": 27,
      "n": 77,
      "net_units": 0.15399999999999958,
      "odds_count": 10,
      "odds_sum": 643.0,
      "pushes": 0,
      "roi": 0.0029615384615384534,
      "sources_combo": "action|juicereel_nukethebooks",
      "total_stake": 52.0,
      "units_missing_count": 25,
      "wilson_lower": 0.538,
      "win_pct": 0.6493506493506493,
      "wins": 50
    },
    {
      "avg_odds": -114.8,
      "bets_with_units": 42,
      "losses": 25,
      "n": 49,
      "net_units": -4.691000000000001,
      "odds_count": 5,
      "odds_sum": -574.0,
      "pushes": 0,
      "roi": -0.1116904761904762,
      "sources_combo": "betql|sportsline",
      "total_stake": 42.0,
      "units_missing_count": 7,
      "wilson_lower": 0.3557,
      "win_pct": 0.4897959183673469,
      "wins": 24
    },
    {
      "avg_odds": 65.4,
      "bets_with_units": 26,
      "losses": 18,
      "n": 42,
      "net_units": -9.383,
      "odds_count": 5,
      "odds_sum": 327.0,
      "pushes": 0,
      "roi": -0.36088461538461536,
      "sources_combo": "action|juicereel_sxebets",
      "total_stake": 26.0,
      "units_missing_count": 16,
      "wilson_lower": 0.4221,
      "win_pct": 0.5714285714285714,
      "wins": 24
    },
    {
      "avg_odds": -105.75,
      "bets_with_units": 35,
      "losses": 22,
      "n": 39,
      "net_units": -10.649999999999999,
      "odds_count": 4,
      "odds_sum": -423.0,
      "pushes": 0,
      "roi": -0.30428571428571427,
      "sources_combo": "betql|dimers",
      "total_stake": 35.0,
      "units_missing_count": 4,
      "wilson_lower": 0.293,
      "win_pct": 0.4358974358974359,
      "wins": 17
    },
    {
      "avg_odds": null,
      "bets_with_units": 36,
      "losses": 21,
      "n": 37,
      "net_units": -3.153,
      "odds_count": 0,
      "odds_sum": 0.0,
      "pushes": 1,
      "roi": -0.08758333333333333,
      "sources_combo": "juicereel_nukethebooks|juicereel_sxebets",
      "total_stake": 36.0,
      "units_missing_count": 1,
      "wilson_lower": 0.2714,
      "win_pct": 0.4166666666666667,
      "wins": 15
    },
    {
      "avg_odds": -112.25,
      "bets_with_units": 32,
      "losses": 19,
      "n": 36,
      "net_units": -8.221,
      "odds_count": 8,
      "odds_sum": -898.0,
      "pushes": 1,
      "roi": -0.25690625,
      "sources_combo": "action|betql|dimers|oddstrader|sportscapping",
      "total_stake": 32.0,
      "units_missing_count": 4,
      "wilson_lower": 0.3047,
      "win_pct": 0.45714285714285713,
      "wins": 16
    },
    {
      "avg_odds": -105.0,
      "bets_with_units": 29,
      "losses": 22,
      "n": 34,
      "net_units": -14.012,
      "odds_count": 1,
      "odds_sum": -105.0,
      "pushes": 0,
      "roi": -0.48317241379310344,
      "sources_combo": "action|betql|covers|oddstrader",
      "total_stake": 29.0,
      "units_missing_count": 5,
      "wilson_lower": 0.2149,
      "win_pct": 0.35294117647058826,
      "wins": 12
    },
    {
      "avg_odds": -50.0,
      "bets_with_units": 28,
      "losses": 17,
      "n": 31,
      "net_units": -6.533,
      "odds_count": 20,
      "odds_sum": -1000.0,
      "pushes": 0,
      "roi": -0.2333214285714286,
      "sources_combo": "action|covers",
      "total_stake": 28.0,
      "units_missing_count": 3,
      "wilson_lower": 0.2916,
      "win_pct": 0.45161290322580644,
      "wins": 14
    },
    {
      "avg_odds": -94.6,
      "bets_with_units": 29,
      "losses": 18,
      "n": 31,
      "net_units": -8.697000000000001,
      "odds_count": 25,
      "odds_sum": -2365.0,
      "pushes": 0,
      "roi": -0.299896551724138,
      "sources_combo": "betql|juicereel_nukethebooks",
      "total_stake": 29.0,
      "units_missing_count": 2,
      "wilson_lower": 0.2642,
      "win_pct": 0.41935483870967744,
      "wins": 13
    },
    {
      "avg_odds": -25.772727272727273,
      "bets_with_units": 26,
      "losses": 14,
      "n": 29,
      "net_units": -2.9499999999999997,
      "odds_count": 22,
      "odds_sum": -567.0,
      "pushes": 1,
      "roi": -0.11346153846153845,
      "sources_combo": "betql|covers",
      "total_stake": 26.0,
      "units_missing_count": 3,
      "wilson_lower": 0.3263,
      "win_pct": 0.5,
      "wins": 14
    },
    {
      "avg_odds": -115.0,
      "bets_with_units": 22,
      "losses": 12,
      "n": 27,
      "net_units": -0.9679999999999999,
      "odds_count": 1,
      "odds_sum": -115.0,
      "pushes": 0,
      "roi": -0.04399999999999999,
      "sources_combo": "juicereel_nukethebooks|oddstrader",
      "total_stake": 22.0,
      "units_missing_count": 5,
      "wilson_lower": 0.3731,
      "win_pct": 0.5555555555555556,
      "wins": 15
    },
    {
      "avg_odds": -94.53333333333333,
      "bets_with_units": 21,
      "losses": 14,
      "n": 24,
      "net_units": -7.603999999999997,
      "odds_count": 15,
      "odds_sum": -1418.0,
      "pushes": 0,
      "roi": -0.36209523809523797,
      "sources_combo": "action|betql|juicereel_nukethebooks",
      "total_stake": 21.0,
      "units_missing_count": 3,
      "wilson_lower": 0.2447,
      "win_pct": 0.4166666666666667,
      "wins": 10
    },
    {
      "avg_odds": -108.33333333333333,
      "bets_with_units": 18,
      "losses": 8,
      "n": 24,
      "net_units": 0.16300000000000026,
      "odds_count": 6,
      "odds_sum": -650.0,
      "pushes": 1,
      "roi": 0.00905555555555557,
      "sources_combo": "action|betql|oddstrader|sportscapping",
      "total_stake": 18.0,
      "units_missing_count": 6,
      "wilson_lower": 0.4489,
      "win_pct": 0.6521739130434783,
      "wins": 15
    },
    {
      "avg_odds": -110.0,
      "bets_with_units": 16,
      "losses": 8,
      "n": 23,
      "net_units": -0.7319999999999998,
      "odds_count": 3,
      "odds_sum": -330.0,
      "pushes": 0,
      "roi": -0.045749999999999985,
      "sources_combo": "action|betql|oddstrader|sportsline",
      "total_stake": 16.0,
      "units_missing_count": 7,
      "wilson_lower": 0.4489,
      "win_pct": 0.6521739130434783,
      "wins": 15
    },
    {
      "avg_odds": 194.0,
      "bets_with_units": 20,
      "losses": 5,
      "n": 22,
      "net_units": 14.49,
      "odds_count": 6,
      "odds_sum": 1164.0,
      "pushes": 0,
      "roi": 0.7245,
      "sources_combo": "action|juicereel_nukethebooks|oddstrader",
      "total_stake": 20.0,
      "units_missing_count": 2,
      "wilson_lower": 0.5656,
      "win_pct": 0.7727272727272727,
      "wins": 17
    },
    {
      "avg_odds": -120.0,
      "bets_with_units": 16,
      "losses": 10,
      "n": 19,
      "net_units": -6.51,
      "odds_count": 1,
      "odds_sum": -120.0,
      "pushes": 0,
      "roi": -0.406875,
      "sources_combo": "juicereel_sxebets|oddstrader",
      "total_stake": 16.0,
      "units_missing_count": 3,
      "wilson_lower": 0.2733,
      "win_pct": 0.47368421052631576,
      "wins": 9
    },
    {
      "avg_odds": -108.6,
      "bets_with_units": 14,
      "losses": 11,
      "n": 17,
      "net_units": -9.207,
      "odds_count": 5,
      "odds_sum": -543.0,
      "pushes": 1,
      "roi": -0.6576428571428572,
      "sources_combo": "action|betql|covers",
      "total_stake": 14.0,
      "units_missing_count": 3,
      "wilson_lower": 0.1416,
      "win_pct": 0.3125,
      "wins": 5
    },
    {
      "avg_odds": -60.5,
      "bets_with_units": 12,
      "losses": 6,
      "n": 14,
      "net_units": 0.10499999999999987,
      "odds_count": 8,
      "odds_sum": -484.0,
      "pushes": 0,
      "roi": 0.008749999999999989,
      "sources_combo": "action|betql|juicereel_sxebets",
      "total_stake": 12.0,
      "units_missing_count": 2,
      "wilson_lower": 0.3259,
      "win_pct": 0.5714285714285714,
      "wins": 8
    },
    {
      "avg_odds": null,
      "bets_with_units": 9,
      "losses": 7,
      "n": 13,
      "net_units": -5.182,
      "odds_count": 0,
      "odds_sum": 0.0,
      "pushes": 0,
      "roi": -0.5757777777777778,
      "sources_combo": "action|betql|covers|vegasinsider",
      "total_stake": 9.0,
      "units_missing_count": 4,
      "wilson_lower": 0.2321,
      "win_pct": 0.46153846153846156,
      "wins": 6
    },
    {
      "avg_odds": -116.83333333333333,
      "bets_with_units": 10,
      "losses": 3,
      "n": 13,
      "net_units": 3.3589999999999995,
      "odds_count": 6,
      "odds_sum": -701.0,
      "pushes": 0,
      "roi": 0.3359,
      "sources_combo": "action|sportsline",
      "total_stake": 10.0,
      "units_missing_count": 3,
      "wilson_lower": 0.4974,
      "win_pct": 0.7692307692307693,
      "wins": 10
    },
    {
      "avg_odds": -108.8,
      "bets_with_units": 9,
      "losses": 7,
      "n": 13,
      "net_units": -5.214,
      "odds_count": 5,
      "odds_sum": -544.0,
      "pushes": 0,
      "roi": -0.5793333333333334,
      "sources_combo": "betql|covers|oddstrader",
      "total_stake": 9.0,
      "units_missing_count": 4,
      "wilson_lower": 0.2321,
      "win_pct": 0.46153846153846156,
      "wins": 6
    },
    {
      "avg_odds": -112.5,
      "bets_with_units": 4,
      "losses": 2,
      "n": 11,
      "net_units": -1.17,
      "odds_count": 2,
      "odds_sum": -225.0,
      "pushes": 1,
      "roi": -0.2925,
      "sources_combo": "action|betql|covers|dimers|oddstrader|sportsline|vegasinsider",
      "total_stake": 4.0,
      "units_missing_count": 7,
      "wilson_lower": 0.4902,
      "win_pct": 0.8,
      "wins": 8
    },
    {
      "avg_odds": -110.0,
      "bets_with_units": 7,
      "losses": 3,
      "n": 11,
      "net_units": -0.1519999999999998,
      "odds_count": 1,
      "odds_sum": -110.0,
      "pushes": 1,
      "roi": -0.021714285714285686,
      "sources_combo": "action|betql|oddstrader|sportsline|vegasinsider",
      "total_stake": 7.0,
      "units_missing_count": 4,
      "wilson_lower": 0.3968,
      "win_pct": 0.7,
      "wins": 7
    },
    {
      "avg_odds": null,
      "bets_with_units": 9,
      "losses": 7,
      "n": 11,
      "net_units": -5.635,
      "odds_count": 0,
      "odds_sum": 0.0,
      "pushes": 0,
      "roi": -0.6261111111111111,
      "sources_combo": "action|juicereel_nukethebooks|juicereel_sxebets",
      "total_stake": 9.0,
      "units_missing_count": 2,
      "wilson_lower": 0.1517,
      "win_pct": 0.36363636363636365,
      "wins": 4
    },
    {
      "avg_odds": 7.5,
      "bets_with_units": 8,
      "losses": 3,
      "n": 10,
      "net_units": 1.694,
      "odds_count": 2,
      "odds_sum": 15.0,
      "pushes": 0,
      "roi": 0.21175,
      "sources_combo": "action|juicereel_sxebets|oddstrader",
      "total_stake": 8.0,
      "units_missing_count": 2,
      "wilson_lower": 0.3968,
      "win_pct": 0.7,
      "wins": 7
    },
    {
      "avg_odds": null,
      "bets_with_units": 10,
      "losses": 2,
      "n": 10,
      "net_units": 4.273,
      "odds_count": 0,
      "odds_sum": 0.0,
      "pushes": 0,
      "roi": 0.42729999999999996,
      "sources_combo": "covers|juicereel_nukethebooks",
      "total_stake": 10.0,
      "units_missing_count": 0,
      "wilson_lower": 0.4902,
      "win_pct": 0.8,
      "wins": 8
    },
    {
      "avg_odds": null,
      "bets_with_units": 8,
      "losses": 6,
      "n": 9,
      "net_units": -2.732,
      "odds_count": 0,
      "odds_sum": 0.0,
      "pushes": 0,
      "roi": -0.3415,
      "sources_combo": "covers|juicereel_sxebets",
      "total_stake": 8.0,
      "units_missing_count": 1,
      "wilson_lower": 0.1206,
      "win_pct": 0.3333333333333333,
      "wins": 3
    },
    {
      "avg_odds": -125.0,
      "bets_with_units": 8,
      "losses": 4,
      "n": 8,
      "net_units": -0.353,
      "odds_count": 1,
      "odds_sum": -125.0,
      "pushes": 0,
      "roi": -0.044125,
      "sources_combo": "action|dimers|juicereel_sxebets",
      "total_stake": 8.0,
      "units_missing_count": 0,
      "wilson_lower": 0.2152,
      "win_pct": 0.5,
      "wins": 4
    },
    {
      "avg_odds": -112.4,
      "bets_with_units": 5,
      "losses": 1,
      "n": 8,
      "net_units": 2.713,
      "odds_count": 5,
      "odds_sum": -562.0,
      "pushes": 0,
      "roi": 0.5426,
      "sources_combo": "action|vegasinsider",
      "total_stake": 5.0,
      "units_missing_count": 3,
      "wilson_lower": 0.5291,
      "win_pct": 0.875,
      "wins": 7
    },
    {
      "avg_odds": -110.0,
      "bets_with_units": 4,
      "losses": 4,
      "n": 8,
      "net_units": -4.05,
      "odds_count": 1,
      "odds_sum": -110.0,
      "pushes": 0,
      "roi": -1.0125,
      "sources_combo": "betql|dimers|oddstrader|vegasinsider",
      "total_stake": 4.0,
      "units_missing_count": 4,
      "wilson_lower": 0.2152,
      "win_pct": 0.5,
      "wins": 4
    },
    {
      "avg_odds": -107.5,
      "bets_with_units": 7,
      "losses": 5,
      "n": 8,
      "net_units": -4.035,
      "odds_count": 4,
      "odds_sum": -430.0,
      "pushes": 0,
      "roi": -0.5764285714285714,
      "sources_combo": "betql|vegasinsider",
      "total_stake": 7.0,
      "units_missing_count": 1,
      "wilson_lower": 0.1368,
      "win_pct": 0.375,
      "wins": 3
    },
    {
      "avg_odds": null,
      "bets_with_units": 6,
      "losses": 2,
      "n": 7,
      "net_units": 0.9009999999999999,
      "odds_count": 0,
      "odds_sum": 0.0,
      "pushes": 0,
      "roi": 0.15016666666666664,
      "sources_combo": "action|betql|dimers|oddstrader|sportsline",
      "total_stake": 6.0,
      "units_missing_count": 1,
      "wilson_lower": 0.3589,
      "win_pct": 0.7142857142857143,
      "wins": 5
    },
    {
      "avg_odds": -58.5,
      "bets_with_units": 7,
      "losses": 2,
      "n": 7,
      "net_units": 3.5690000000000004,
      "odds_count": 6,
      "odds_sum": -351.0,
      "pushes": 0,
      "roi": 0.5098571428571429,
      "sources_combo": "action|covers|vegasinsider",
      "total_stake": 7.0,
      "units_missing_count": 0,
      "wilson_lower": 0.3589,
      "win_pct": 0.7142857142857143,
      "wins": 5
    },
    {
      "avg_odds": -108.33333333333333,
      "bets_with_units": 7,
      "losses": 5,
      "n": 7,
      "net_units": -3.124,
      "odds_count": 3,
      "odds_sum": -325.0,
      "pushes": 0,
      "roi": -0.4462857142857143,
      "sources_combo": "action|oddstrader|vegasinsider",
      "total_stake": 7.0,
      "units_missing_count": 0,
      "wilson_lower": 0.0822,
      "win_pct": 0.2857142857142857,
      "wins": 2
    },
    {
      "avg_odds": -111.5,
      "bets_with_units": 7,
      "losses": 3,
      "n": 7,
      "net_units": 0.6099999999999999,
      "odds_count": 6,
      "odds_sum": -669.0,
      "pushes": 0,
      "roi": 0.08714285714285712,
      "sources_combo": "sportsline|vegasinsider",
      "total_stake": 7.0,
      "units_missing_count": 0,
      "wilson_lower": 0.2505,
      "win_pct": 0.5714285714285714,
      "wins": 4
    },
    {
      "avg_odds": -3.7142857142857144,
      "bets_with_units": 7,
      "losses": 4,
      "n": 7,
      "net_units": -0.43199999999999983,
      "odds_count": 7,
      "odds_sum": -26.0,
      "pushes": 0,
      "roi": -0.06171428571428569,
      "sources_combo": "vegasinsider",
      "total_stake": 7.0,
      "units_missing_count": 0,
      "wilson_lower": 0.1582,
      "win_pct": 0.42857142857142855,
      "wins": 3
    },
    {
      "avg_odds": -112.5,
      "bets_with_units": 4,
      "losses": 4,
      "n": 6,
      "net_units": -4.18,
      "odds_count": 2,
      "odds_sum": -225.0,
      "pushes": 0,
      "roi": -1.045,
      "sources_combo": "action|betql|sportsline",
      "total_stake": 4.0,
      "units_missing_count": 2,
      "wilson_lower": 0.0968,
      "win_pct": 0.3333333333333333,
      "wins": 2
    },
    {
      "avg_odds": -28.6,
      "bets_with_units": 6,
      "losses": 4,
      "n": 6,
      "net_units": -1.088,
      "odds_count": 5,
      "odds_sum": -143.0,
      "pushes": 0,
      "roi": -0.18133333333333335,
      "sources_combo": "covers|vegasinsider",
      "total_stake": 6.0,
      "units_missing_count": 0,
      "wilson_lower": 0.0968,
      "win_pct": 0.3333333333333333,
      "wins": 2
    },
    {
      "avg_odds": null,
      "bets_with_units": 5,
      "losses": 2,
      "n": 6,
      "net_units": 0.7430000000000001,
      "odds_count": 0,
      "odds_sum": 0.0,
      "pushes": 0,
      "roi": 0.1486,
      "sources_combo": "dimers|juicereel_sxebets|oddstrader",
      "total_stake": 5.0,
      "units_missing_count": 1,
      "wilson_lower": 0.3,
      "win_pct": 0.6666666666666666,
      "wins": 4
    },
    {
      "avg_odds": null,
      "bets_with_units": 5,
      "losses": 4,
      "n": 6,
      "net_units": -3.051,
      "odds_count": 0,
      "odds_sum": 0.0,
      "pushes": 0,
      "roi": -0.6102000000000001,
      "sources_combo": "oddstrader|sportsline",
      "total_stake": 5.0,
      "units_missing_count": 1,
      "wilson_lower": 0.0968,
      "win_pct": 0.3333333333333333,
      "wins": 2
    },
    {
      "avg_odds": -111.5,
      "bets_with_units": 5,
      "losses": 5,
      "n": 5,
      "net_units": -5.11,
      "odds_count": 2,
      "odds_sum": -223.0,
      "pushes": 0,
      "roi": -1.022,
      "sources_combo": "action|betql|dimers|vegasinsider",
      "total_stake": 5.0,
      "units_missing_count": 0,
      "wilson_lower": -0.0,
      "win_pct": 0.0,
      "wins": 0
    },
    {
      "avg_odds": -112.0,
      "bets_with_units": 1,
      "losses": 0,
      "n": 5,
      "net_units": 0.946,
      "odds_count": 1,
      "odds_sum": -112.0,
      "pushes": 0,
      "roi": 0.946,
      "sources_combo": "action|betql|vegasinsider",
      "total_stake": 1.0,
      "units_missing_count": 4,
      "wilson_lower": 0.5655,
      "win_pct": 1.0,
      "wins": 5
    },
    {
      "avg_odds": -110.0,
      "bets_with_units": 4,
      "losses": 1,
      "n": 5,
      "net_units": 1.72,
      "odds_count": 1,
      "odds_sum": -110.0,
      "pushes": 0,
      "roi": 0.43,
      "sources_combo": "action|oddstrader|sportsline",
      "total_stake": 4.0,
      "units_missing_count": 1,
      "wilson_lower": 0.3755,
      "win_pct": 0.8,
      "wins": 4
    },
    {
      "avg_odds": 0.0,
      "bets_with_units": 4,
      "losses": 1,
      "n": 5,
      "net_units": 2.0010000000000003,
      "odds_count": 4,
      "odds_sum": 0.0,
      "pushes": 0,
      "roi": 0.5002500000000001,
      "sources_combo": "betql|covers|dimers",
      "total_stake": 4.0,
      "units_missing_count": 1,
      "wilson_lower": 0.3755,
      "win_pct": 0.8,
      "wins": 4
    },
    {
      "avg_odds": -110.0,
      "bets_with_units": 3,
      "losses": 0,
      "n": 5,
      "net_units": 2.856,
      "odds_count": 1,
      "odds_sum": -110.0,
      "pushes": 0,
      "roi": 0.952,
      "sources_combo": "betql|oddstrader|sportsline",
      "total_stake": 3.0,
      "units_missing_count": 2,
      "wilson_lower": 0.5655,
      "win_pct": 1.0,
      "wins": 5
    },
    {
      "avg_odds": -115.0,
      "bets_with_units": 3,
      "losses": 2,
      "n": 4,
      "net_units": -1.1340000000000001,
      "odds_count": 2,
      "odds_sum": -230.0,
      "pushes": 0,
      "roi": -0.37800000000000006,
      "sources_combo": "action|betql|sportsline|vegasinsider",
      "total_stake": 3.0,
      "units_missing_count": 1,
      "wilson_lower": 0.15,
      "win_pct": 0.5,
      "wins": 2
    },
    {
      "avg_odds": -110.0,
      "bets_with_units": 3,
      "losses": 1,
      "n": 4,
      "net_units": 0.864,
      "odds_count": 1,
      "odds_sum": -110.0,
      "pushes": 0,
      "roi": 0.288,
      "sources_combo": "action|covers|oddstrader|sportsline|vegasinsider",
      "total_stake": 3.0,
      "units_missing_count": 1,
      "wilson_lower": 0.3006,
      "win_pct": 0.75,
      "wins": 3
    },
    {
      "avg_odds": -110.0,
      "bets_with_units": 4,
      "losses": 4,
      "n": 4,
      "net_units": -3.44,
      "odds_count": 1,
      "odds_sum": -110.0,
      "pushes": 0,
      "roi": -0.86,
      "sources_combo": "action|dimers|juicereel_nukethebooks|oddstrader",
      "total_stake": 4.0,
      "units_missing_count": 0,
      "wilson_lower": 0.0,
      "win_pct": 0.0,
      "wins": 0
    },
    {
      "avg_odds": -118.0,
      "bets_with_units": 4,
      "losses": 3,
      "n": 4,
      "net_units": -2.069,
      "odds_count": 3,
      "odds_sum": -354.0,
      "pushes": 0,
      "roi": -0.51725,
      "sources_combo": "betql|juicereel_nukethebooks|juicereel_sxebets",
      "total_stake": 4.0,
      "units_missing_count": 0,
      "wilson_lower": 0.0456,
      "win_pct": 0.25,
      "wins": 1
    },
    {
      "avg_odds": 42.0,
      "bets_with_units": 3,
      "losses": 1,
      "n": 4,
      "net_units": 1.112,
      "odds_count": 3,
      "odds_sum": 126.0,
      "pushes": 0,
      "roi": 0.3706666666666667,
      "sources_combo": "covers|dimers",
      "total_stake": 3.0,
      "units_missing_count": 1,
      "wilson_lower": 0.3006,
      "win_pct": 0.75,
      "wins": 3
    },
    {
      "avg_odds": -41.666666666666664,
      "bets_with_units": 4,
      "losses": 2,
      "n": 4,
      "net_units": -0.17100000000000004,
      "odds_count": 3,
      "odds_sum": -125.0,
      "pushes": 0,
      "roi": -0.04275000000000001,
      "sources_combo": "covers|sportsline",
      "total_stake": 4.0,
      "units_missing_count": 0,
      "wilson_lower": 0.15,
      "win_pct": 0.5,
      "wins": 2
    },
    {
      "avg_odds": null,
      "bets_with_units": 4,
      "losses": 2,
      "n": 4,
      "net_units": -2.124,
      "odds_count": 0,
      "odds_sum": 0.0,
      "pushes": 0,
      "roi": -0.531,
      "sources_combo": "dimers|juicereel_nukethebooks",
      "total_stake": 4.0,
      "units_missing_count": 0,
      "wilson_lower": 0.15,
      "win_pct": 0.5,
      "wins": 2
    },
    {
      "avg_odds": null,
      "bets_with_units": 4,
      "losses": 2,
      "n": 4,
      "net_units": -0.86,
      "odds_count": 0,
      "odds_sum": 0.0,
      "pushes": 0,
      "roi": -0.215,
      "sources_combo": "dimers|juicereel_nukethebooks|oddstrader",
      "total_stake": 4.0,
      "units_missing_count": 0,
      "wilson_lower": 0.15,
      "win_pct": 0.5,
      "wins": 2
    },
    {
      "avg_odds": -109.5,
      "bets_with_units": 4,
      "losses": 2,
      "n": 4,
      "net_units": -0.18400000000000016,
      "odds_count": 4,
      "odds_sum": -438.0,
      "pushes": 0,
      "roi": -0.04600000000000004,
      "sources_combo": "oddstrader|vegasinsider",
      "total_stake": 4.0,
      "units_missing_count": 0,
      "wilson_lower": 0.15,
      "win_pct": 0.5,
      "wins": 2
    },
    {
      "avg_odds": -110.0,
      "bets_with_units": 3,
      "losses": 3,
      "n": 3,
      "net_units": -3.12,
      "odds_count": 1,
      "odds_sum": -110.0,
      "pushes": 0,
      "roi": -1.04,
      "sources_combo": "action|betql|dimers|sportsline",
      "total_stake": 3.0,
      "units_missing_count": 0,
      "wilson_lower": 0.0,
      "win_pct": 0.0,
      "wins": 0
    },
    {
      "avg_odds": -7.5,
      "bets_with_units": 3,
      "losses": 1,
      "n": 3,
      "net_units": 0.805,
      "odds_count": 2,
      "odds_sum": -15.0,
      "pushes": 0,
      "roi": 0.26833333333333337,
      "sources_combo": "action|covers|oddstrader",
      "total_stake": 3.0,
      "units_missing_count": 0,
      "wilson_lower": 0.2077,
      "win_pct": 0.6666666666666666,
      "wins": 2
    },
    {
      "avg_odds": null,
      "bets_with_units": 3,
      "losses": 3,
      "n": 3,
      "net_units": -2.5599999999999996,
      "odds_count": 0,
      "odds_sum": 0.0,
      "pushes": 0,
      "roi": -0.8533333333333332,
      "sources_combo": "action|dimers|juicereel_nukethebooks",
      "total_stake": 3.0,
      "units_missing_count": 0,
      "wilson_lower": 0.0,
      "win_pct": 0.0,
      "wins": 0
    },
    {
      "avg_odds": -122.0,
      "bets_with_units": 3,
      "losses": 0,
      "n": 3,
      "net_units": 2.46,
      "odds_count": 1,
      "odds_sum": -122.0,
      "pushes": 0,
      "roi": 0.82,
      "sources_combo": "action|dimers|sportsline",
      "total_stake": 3.0,
      "units_missing_count": 0,
      "wilson_lower": 0.4385,
      "win_pct": 1.0,
      "wins": 3
    },
    {
      "avg_odds": -118.5,
      "bets_with_units": 3,
      "losses": 3,
      "n": 3,
      "net_units": -3.1700000000000004,
      "odds_count": 2,
      "odds_sum": -237.0,
      "pushes": 0,
      "roi": -1.0566666666666669,
      "sources_combo": "action|dimers|vegasinsider",
      "total_stake": 3.0,
      "units_missing_count": 0,
      "wilson_lower": 0.0,
      "win_pct": 0.0,
      "wins": 0
    },
    {
      "avg_odds": -106.0,
      "bets_with_units": 3,
      "losses": 3,
      "n": 3,
      "net_units": -3.0599999999999996,
      "odds_count": 2,
      "odds_sum": -212.0,
      "pushes": 0,
      "roi": -1.0199999999999998,
      "sources_combo": "betql|dimers|sportsline|vegasinsider",
      "total_stake": 3.0,
      "units_missing_count": 0,
      "wilson_lower": 0.0,
      "win_pct": 0.0,
      "wins": 0
    },
    {
      "avg_odds": -106.0,
      "bets_with_units": 2,
      "losses": 2,
      "n": 3,
      "net_units": -2.0300000000000002,
      "odds_count": 1,
      "odds_sum": -106.0,
      "pushes": 0,
      "roi": -1.0150000000000001,
      "sources_combo": "betql|dimers|vegasinsider",
      "total_stake": 2.0,
      "units_missing_count": 1,
      "wilson_lower": 0.0615,
      "win_pct": 0.3333333333333333,
      "wins": 1
    },
    {
      "avg_odds": -117.33333333333333,
      "bets_with_units": 3,
      "losses": 3,
      "n": 3,
      "net_units": -3.24,
      "odds_count": 3,
      "odds_sum": -352.0,
      "pushes": 0,
      "roi": -1.08,
      "sources_combo": "betql|juicereel_nukethebooks|oddstrader",
      "total_stake": 3.0,
      "units_missing_count": 0,
      "wilson_lower": 0.0,
      "win_pct": 0.0,
      "wins": 0
    },
    {
      "avg_odds": -112.0,
      "bets_with_units": 3,
      "losses": 2,
      "n": 3,
      "net_units": -1.054,
      "odds_count": 1,
      "odds_sum": -112.0,
      "pushes": 0,
      "roi": -0.35133333333333333,
      "sources_combo": "betql|oddstrader|sportscapping|sportsline",
      "total_stake": 3.0,
      "units_missing_count": 0,
      "wilson_lower": 0.0615,
      "win_pct": 0.3333333333333333,
      "wins": 1
    },
    {
      "avg_odds": -110.0,
      "bets_with_units": 3,
      "losses": 3,
      "n": 3,
      "net_units": -3.05,
      "odds_count": 1,
      "odds_sum": -110.0,
      "pushes": 0,
      "roi": -1.0166666666666666,
      "sources_combo": "betql|sportscapping",
      "total_stake": 3.0,
      "units_missing_count": 0,
      "wilson_lower": 0.0,
      "win_pct": 0.0,
      "wins": 0
    },
    {
      "avg_odds": null,
      "bets_with_units": 1,
      "losses": 0,
      "n": 2,
      "net_units": 0.972,
      "odds_count": 0,
      "odds_sum": 0.0,
      "pushes": 0,
      "roi": 0.972,
      "sources_combo": "betql|dimers|sportsline",
      "total_stake": 1.0,
      "units_missing_count": 1,
      "wilson_lower": 0.3424,
      "win_pct": 1.0,
      "wins": 2
    },
    {
      "avg_odds": -118.0,
      "bets_with_units": 2,
      "losses": 0,
      "n": 2,
      "net_units": 1.0350000000000001,
      "odds_count": 1,
      "odds_sum": -118.0,
      "pushes": 0,
      "roi": 0.5175000000000001,
      "sources_combo": "betql|sportsline|vegasinsider",
      "total_stake": 2.0,
      "units_missing_count": 0,
      "wilson_lower": 0.3424,
      "win_pct": 1.0,
      "wins": 2
    },
    {
      "avg_odds": -118.0,
      "bets_with_units": 1,
      "losses": 0,
      "n": 2,
      "net_units": 0.915,
      "odds_count": 1,
      "odds_sum": -118.0,
      "pushes": 0,
      "roi": 0.915,
      "sources_combo": "covers|dimers|vegasinsider",
      "total_stake": 1.0,
      "units_missing_count": 1,
      "wilson_lower": 0.3424,
      "win_pct": 1.0,
      "wins": 2
    },
    {
      "avg_odds": -120.0,
      "bets_with_units": 2,
      "losses": 1,
      "n": 2,
      "net_units": -0.09199999999999997,
      "odds_count": 1,
      "odds_sum": -120.0,
      "pushes": 0,
      "roi": -0.045999999999999985,
      "sources_combo": "covers|oddstrader",
      "total_stake": 2.0,
      "units_missing_count": 0,
      "wilson_lower": 0.0945,
      "win_pct": 0.5,
      "wins": 1
    },
    {
      "avg_odds": -115.0,
      "bets_with_units": 2,
      "losses": 1,
      "n": 2,
      "net_units": -0.12,
      "odds_count": 1,
      "odds_sum": -115.0,
      "pushes": 0,
      "roi": -0.06,
      "sources_combo": "sportscapping|sportsline",
      "total_stake": 2.0,
      "units_missing_count": 0,
      "wilson_lower": 0.0945,
      "win_pct": 0.5,
      "wins": 1
    },
    {
      "avg_odds": null,
      "bets_with_units": 0,
      "losses": 0,
      "n": 1,
      "net_units": 0.0,
      "odds_count": 0,
      "odds_sum": 0.0,
      "pushes": 0,
      "roi": null,
      "sources_combo": "action|betql|covers|dimers|juicereel_sxebets",
      "total_stake": 0.0,
      "units_missing_count": 1,
      "wilson_lower": 0.2065,
      "win_pct": 1.0,
      "wins": 1
    },
    {
      "avg_odds": null,
      "bets_with_units": 1,
      "losses": 1,
      "n": 1,
      "net_units": -1.0,
      "odds_count": 0,
      "odds_sum": 0.0,
      "pushes": 0,
      "roi": -1.0,
      "sources_combo": "action|betql|covers|juicereel_sxebets",
      "total_stake": 1.0,
      "units_missing_count": 0,
      "wilson_lower": 0.0,
      "win_pct": 0.0,
      "wins": 0
    },
    {
      "avg_odds": -129.0,
      "bets_with_units": 1,
      "losses": 1,
      "n": 1,
      "net_units": -1.0,
      "odds_count": 1,
      "odds_sum": -129.0,
      "pushes": 0,
      "roi": -1.0,
      "sources_combo": "action|betql|dimers|juicereel_nukethebooks",
      "total_stake": 1.0,
      "units_missing_count": 0,
      "wilson_lower": 0.0,
      "win_pct": 0.0,
      "wins": 0
    },
    {
      "avg_odds": null,
      "bets_with_units": 1,
      "losses": 1,
      "n": 1,
      "net_units": -1.0,
      "odds_count": 0,
      "odds_sum": 0.0,
      "pushes": 0,
      "roi": -1.0,
      "sources_combo": "action|sportsline|vegasinsider",
      "total_stake": 1.0,
      "units_missing_count": 0,
      "wilson_lower": 0.0,
      "win_pct": 0.0,
      "wins": 0
    },
    {
      "avg_odds": -117.0,
      "bets_with_units": 1,
      "losses": 0,
      "n": 1,
      "net_units": 0.93,
      "odds_count": 1,
      "odds_sum": -117.0,
      "pushes": 0,
      "roi": 0.93,
      "sources_combo": "betql|covers|juicereel_nukethebooks",
      "total_stake": 1.0,
      "units_missing_count": 0,
      "wilson_lower": 0.2065,
      "win_pct": 1.0,
      "wins": 1
    },
    {
      "avg_odds": -108.0,
      "bets_with_units": 1,
      "losses": 1,
      "n": 1,
      "net_units": -1.04,
      "odds_count": 1,
      "odds_sum": -108.0,
      "pushes": 0,
      "roi": -1.04,
      "sources_combo": "betql|covers|vegasinsider",
      "total_stake": 1.0,
      "units_missing_count": 0,
      "wilson_lower": 0.0,
      "win_pct": 0.0,
      "wins": 0
    },
    {
      "avg_odds": 112.0,
      "bets_with_units": 1,
      "losses": 1,
      "n": 1,
      "net_units": -0.94,
      "odds_count": 1,
      "odds_sum": 112.0,
      "pushes": 0,
      "roi": -0.94,
      "sources_combo": "dimers|juicereel_sxebets|vegasinsider",
      "total_stake": 1.0,
      "units_missing_count": 0,
      "wilson_lower": 0.0,
      "win_pct": 0.0,
      "wins": 0
    },
    {
      "avg_odds": null,
      "bets_with_units": 1,
      "losses": 1,
      "n": 1,
      "net_units": -1.0,
      "odds_count": 0,
      "odds_sum": 0.0,
      "pushes": 0,
      "roi": -1.0,
      "sources_combo": "dimers|sportsline",
      "total_stake": 1.0,
      "units_missing_count": 0,
      "wilson_lower": 0.0,
      "win_pct": 0.0,
      "wins": 0
    },
    {
      "avg_odds": -110.0,
      "bets_with_units": 1,
      "losses": 1,
      "n": 1,
      "net_units": -1.05,
      "odds_count": 1,
      "odds_sum": -110.0,
      "pushes": 0,
      "roi": -1.05,
      "sources_combo": "dimers|vegasinsider",
      "total_stake": 1.0,
      "units_missing_count": 0,
      "wilson_lower": 0.0,
      "win_pct": 0.0,
      "wins": 0
    },
    {
      "avg_odds": null,
      "bets_with_units": 1,
      "losses": 0,
      "n": 1,
      "net_units": 1.029,
      "odds_count": 0,
      "odds_sum": 0.0,
      "pushes": 0,
      "roi": 1.029,
      "sources_combo": "juicereel_nukethebooks|juicereel_sxebets|oddstrader",
      "total_stake": 1.0,
      "units_missing_count": 0,
      "wilson_lower": 0.2065,
      "win_pct": 1.0,
      "wins": 1
    },
    {
      "avg_odds": null,
      "bets_with_units": 1,
      "losses": 1,
      "n": 1,
      "net_units": -1.0,
      "odds_count": 0,
      "odds_sum": 0.0,
      "pushes": 0,
      "roi": -1.0,
      "sources_combo": "sportscapping",
      "total_stake": 1.0,
      "units_missing_count": 0,
      "wilson_lower": 0.0,
      "win_pct": 0.0,
      "wins": 0
    }
  ]
}